pygada/__init__.py
pygada/data_filtering/__init__.py
pygada/data_input/PFAS_pydov.py
pygada/data_input/__init__.py
pygada/data_input/groundwater_pydov.py
pygada/data_input/soil_pydov.py
pygada/explorative_data_analysis/__init__.py
pygada/kriging_interpolation/__init__.py
pygada-0.1.0.dist-info/AUTHORS.rst
pygada-0.1.0.dist-info/LICENSE
pygada-0.1.0.dist-info/METADATA
pygada-0.1.0.dist-info/WHEEL
pygada-0.1.0.dist-info/top_level.txt
pygada-0.1.0.dist-info/RECORD
