Metadata-Version: 2.1
Name: pygada
Version: 0.1.0
Summary: First release
Author-email: Guillaume Vandekerckhove <guillaume.vandekerckhove@outlook.com>
Project-URL: Source-code, https://github.com/DOV-Vlaanderen/pygada.git
Project-URL: Documentation, https://pygada.readthedocs.io/en/latest/?badge=latest
Classifier: Programming Language :: Python :: 3
Classifier: License :: OSI Approved :: MIT License
Classifier: Operating System :: OS Independent
Requires-Python: >=3.10
License-File: LICENSE
License-File: AUTHORS.rst
